<?xml version="1.0"?>
<opencv_storage>
<cascade>
  <stageType>BOOST</stageType>
  <featureType>LBP</featureType>
  <height>90</height>
  <width>40</width>
  <stageParams>
    <boostType>GAB</boostType>
    <minHitRate>9.9900001287460327e-01</minHitRate>
    <maxFalseAlarm>5.0000000000000000e-01</maxFalseAlarm>
    <weightTrimRate>9.4999999999999996e-01</weightTrimRate>
    <maxDepth>1</maxDepth>
    <maxWeakCount>100</maxWeakCount></stageParams>
  <featureParams>
    <maxCatCount>256</maxCatCount>
    <featSize>1</featSize></featureParams>
  <stageNum>20</stageNum>
  <stages>
    <!-- stage 0 -->
    <_>
      <maxWeakCount>3</maxWeakCount>
      <stageThreshold>-9.6723437309265137e-01</stageThreshold>
      <weakClassifiers>
        <_>
          <internalNodes>
            0 -1 3 1977340367 1342275584 0 1076035584 163850 0 32768
            1359200267</internalNodes>
          <leafValues>
            -9.3739706277847290e-01 9.7583079338073730e-01</leafValues></_>
        <_>
          <internalNodes>
            0 -1 6 -179318037 1073840130 -2147483648 1073971201 131074 0
            1 1392721923</internalNodes>
          <leafValues>
            -9.2053747177124023e-01 9.4663184881210327e-01</leafValues></_>
        <_>
          <internalNodes>
            0 -1 9 -10233345 1397342225 50335768 289603585 8945816 2
            -2130673653 327897807</internalNodes>
          <leafValues>
            -9.8769855499267578e-01 8.9070016145706177e-01</leafValues></_></weakClassifiers></_>
    <!-- stage 1 -->
    <_>
      <maxWeakCount>3</maxWeakCount>
      <stageThreshold>-1.0172735452651978e+00</stageThreshold>
      <weakClassifiers>
        <_>
          <internalNodes>
            0 -1 7 -750261553 290160649 -2147368829 1258545155 537067659
            720897 33603715 834132943</internalNodes>
          <leafValues>
            -9.4263863563537598e-01 8.2915508747100830e-01</leafValues></_>
        <_>
          <internalNodes>
            0 -1 53 -924920417 49331 1073829911 1627557907 1375970699
            213128 -1341472597 -754198081</internalNodes>
          <leafValues>
            -7.9889869689941406e-01 7.7314972877502441e-01</leafValues></_>
        <_>
          <internalNodes>
            0 -1 13 -79169081 -786710509 1073824002 1435992327 37900290
            1342177379 269340737 1968948207</internalNodes>
          <leafValues>
            -7.9694622755050659e-01 7.2426378726959229e-01</leafValues></_></weakClassifiers></_>
    <!-- stage 2 -->
    <_>
      <maxWeakCount>2</maxWeakCount>
      <stageThreshold>-3.0214869976043701e-01</stageThreshold>
      <weakClassifiers>
        <_>
          <internalNodes>
            0 -1 5 -87034929 1493692867 67117073 1393512707 -528154421
            1342390274 1619198347 2146399215</internalNodes>
          <leafValues>
            -9.1170823574066162e-01 8.1093603372573853e-01</leafValues></_>
        <_>
          <internalNodes>
            0 -1 8 -74450021 1998700553 -238423601 1936936977 -927745121
            1393230849 -1978941265 322947355</internalNodes>
          <leafValues>
            -9.4736945629119873e-01 6.0955953598022461e-01</leafValues></_></weakClassifiers></_>
    <!-- stage 3 -->
    <_>
      <maxWeakCount>2</maxWeakCount>
      <stageThreshold>-1.7859587073326111e-01</stageThreshold>
      <weakClassifiers>
        <_>
          <internalNodes>
            0 -1 62 14679039 38797411 -1073168382 391610951 -1073635328
            682508291 1074315403 -24390677</internalNodes>
          <leafValues>
            -8.2773107290267944e-01 7.0640569925308228e-01</leafValues></_>
        <_>
          <internalNodes>
            0 -1 63 -1040154396 -398434237 -1073725149 -770780286
            -1834237298 1895923842 1082376331 -4194993</internalNodes>
          <leafValues>
            -7.9091095924377441e-01 6.4913523197174072e-01</leafValues></_></weakClassifiers></_>
    <!-- stage 4 -->
    <_>
      <maxWeakCount>2</maxWeakCount>
      <stageThreshold>-1.9024369120597839e-01</stageThreshold>
      <weakClassifiers>
        <_>
          <internalNodes>
            0 -1 28 132111327 866844879 389 1498103947 -1207383925
            331556379 -1037332469 1072402415</internalNodes>
          <leafValues>
            -9.0987122058868408e-01 7.2663140296936035e-01</leafValues></_>
        <_>
          <internalNodes>
            0 -1 35 913782135 -112527813 -1910434657 -904743745
            -501316777 -279188261 -360181676 -1091552400</internalNodes>
          <leafValues>
            -7.1378356218338013e-01 7.1962755918502808e-01</leafValues></_></weakClassifiers></_>
    <!-- stage 5 -->
    <_>
      <maxWeakCount>5</maxWeakCount>
      <stageThreshold>-7.3189109563827515e-01</stageThreshold>
      <weakClassifiers>
        <_>
          <internalNodes>
            0 -1 11 -118227713 1932589055 -1 -134217729 -1594425857
            1113599 -704643073 -573046785</internalNodes>
          <leafValues>
            -6.1129570007324219e-01 7.6953905820846558e-01</leafValues></_>
        <_>
          <internalNodes>
            0 -1 22 -201632545 -922234827 -591216350 -233831089
            -997774316 1507889601 1149369460 -842140717</internalNodes>
          <leafValues>
            -6.1822474002838135e-01 7.1777993440628052e-01</leafValues></_>
        <_>
          <internalNodes>
            0 -1 67 -228072457 -620642015 67338252 109641749 -2146176500
            -503267325 -1509252598 714825631</internalNodes>
          <leafValues>
            -8.2083737850189209e-01 5.4258203506469727e-01</leafValues></_>
        <_>
          <internalNodes>
            0 -1 82 -84713505 -558003305 -1223962439 -1370580984
            -1970545819 -83363654 -1369937099 -33549888</internalNodes>
          <leafValues>
            -6.6957783699035645e-01 6.4661204814910889e-01</leafValues></_>
        <_>
          <internalNodes>
            0 -1 29 -73829969 -251117374 -1071415270 1879761094
            1075858756 1153696062 -797982108 -223224932</internalNodes>
          <leafValues>
            -6.6415005922317505e-01 6.9317650794982910e-01</leafValues></_></weakClassifiers></_>
    <!-- stage 6 -->
    <_>
      <maxWeakCount>5</maxWeakCount>
      <stageThreshold>-9.8352551460266113e-01</stageThreshold>
      <weakClassifiers>
        <_>
          <internalNodes>
            0 -1 12 -153946269 1917047179 -1879048191 1233589312
            570556418 4103 407060754 1943490699</internalNodes>
          <leafValues>
            -7.2427982091903687e-01 6.7504489421844482e-01</leafValues></_>
        <_>
          <internalNodes>
            0 -1 24 -8421377 2117599231 -75825166 -1493205021 2138505074
            -137 -138758736 -320374731</internalNodes>
          <leafValues>
            -5.7918220758438110e-01 6.8520665168762207e-01</leafValues></_>
        <_>
          <internalNodes>
            0 -1 41 -310379062 711393279 -268435713 989233083 -966328508
            1683128182 -704751617 -1325662209</internalNodes>
          <leafValues>
            -6.1981630325317383e-01 6.6964554786682129e-01</leafValues></_>
        <_>
          <internalNodes>
            0 -1 38 -1618027565 1526808840 37953 806965509 304242963
            495682733 318902763 533435311</internalNodes>
          <leafValues>
            -7.9966229200363159e-01 5.0822526216506958e-01</leafValues></_>
        <_>
          <internalNodes>
            0 -1 73 -2091662001 542310594 -2147106816 218828815
            -2147340288 1073759232 -1056964351 -1851798833</internalNodes>
          <leafValues>
            -8.1443566083908081e-01 4.8712119460105896e-01</leafValues></_></weakClassifiers></_>
    <!-- stage 7 -->
    <_>
      <maxWeakCount>5</maxWeakCount>
      <stageThreshold>-6.7663943767547607e-01</stageThreshold>
      <weakClassifiers>
        <_>
          <internalNodes>
            0 -1 20 -137363729 -46137473 1870135158 2147483647
            2002020195 1819768695 1083700529 -1996490769</internalNodes>
          <leafValues>
            -6.1129570007324219e-01 7.6953905820846558e-01</leafValues></_>
        <_>
          <internalNodes>
            0 -1 34 -235930129 1319145539 -1862041494 -1501420478
            1880314727 1879408807 -793665179 -189552213</internalNodes>
          <leafValues>
            -6.4600968360900879e-01 6.8384271860122681e-01</leafValues></_>
        <_>
          <internalNodes>
            0 -1 21 -740827409 -443775997 -1006021496 -1824290674
            1919632645 1343160841 1351603504 -1007223809</internalNodes>
          <leafValues>
            -6.5024310350418091e-01 6.9211709499359131e-01</leafValues></_>
        <_>
          <internalNodes>
            0 -1 78 -334372953 4227204 -268427248 541370378 -754724854
            -2097151998 -1056849920 -527442665</internalNodes>
          <leafValues>
            -7.1278196573257446e-01 6.4749050140380859e-01</leafValues></_>
        <_>
          <internalNodes>
            0 -1 57 -1933401969 1242933313 -721371136 -1073626592
            -1055187969 43307040 411617290 -141583877</internalNodes>
          <leafValues>
            -7.1899867057800293e-01 6.1383855342864990e-01</leafValues></_></weakClassifiers></_>
    <!-- stage 8 -->
    <_>
      <maxWeakCount>5</maxWeakCount>
      <stageThreshold>-1.7301286458969116e+00</stageThreshold>
      <weakClassifiers>
        <_>
          <internalNodes>
            0 -1 10 -151391501 1902376887 -1 -134742017 -1325924609
            284159 1979711487 -134219777</internalNodes>
          <leafValues>
            -5.1533740758895874e-01 7.7637130022048950e-01</leafValues></_>
        <_>
          <internalNodes>
            0 -1 42 -335545249 -1360298053 -50331912 -1479737348
            -159908012 -830541954 -142606479 -974788609</internalNodes>
          <leafValues>
            -5.5182862281799316e-01 7.3238950967788696e-01</leafValues></_>
        <_>
          <internalNodes>
            0 -1 49 -16818305 644595707 -1075380366 -1430265942
            -159514767 -453574667 -236716187 -195567663</internalNodes>
          <leafValues>
            -5.6697231531143188e-01 6.8861681222915649e-01</leafValues></_>
        <_>
          <internalNodes>
            0 -1 23 -304128265 -2115706553 -2097114541 283299936
            -1551035325 -898858414 834859874 -73373583</internalNodes>
          <leafValues>
            -6.3607501983642578e-01 6.5356963872909546e-01</leafValues></_>
        <_>
          <internalNodes>
            0 -1 70 -877306889 -1983397744 1846628592 -290815886
            -1291612075 172851490 -854603660 -51609616</internalNodes>
          <leafValues>
            -7.5162398815155029e-01 5.3969955444335938e-01</leafValues></_></weakClassifiers></_>
    <!-- stage 9 -->
    <_>
      <maxWeakCount>6</maxWeakCount>
      <stageThreshold>-1.4097422361373901e+00</stageThreshold>
      <weakClassifiers>
        <_>
          <internalNodes>
            0 -1 1 -875047125 -503115776 67141634 -1069317948 1126204584
            1082229760 -805273600 1475081151</internalNodes>
          <leafValues>
            -7.2860127687454224e-01 6.6815340518951416e-01</leafValues></_>
        <_>
          <internalNodes>
            0 -1 27 -208667393 1375961230 82051 1090765963 1073832005
            1076073001 1090904321 1430769647</internalNodes>
          <leafValues>
            -7.5023740530014038e-01 5.5479604005813599e-01</leafValues></_>
        <_>
          <internalNodes>
            0 -1 25 -448027209 1078487078 -2080343802 -1304133322
            -2133988269 1611171106 -939284479 -409508827</internalNodes>
          <leafValues>
            -6.8096280097961426e-01 6.0432434082031250e-01</leafValues></_>
        <_>
          <internalNodes>
            0 -1 18 -423954945 1282736125 -487915958 -956760321 -41122
            -831226019 -134817930 -405211777</internalNodes>
          <leafValues>
            -5.7070618867874146e-01 7.2057008743286133e-01</leafValues></_>
        <_>
          <internalNodes>
            0 -1 89 -12854273 178840304 -1342247504 -189741968 402579276
            -1612812292 2147384692 -1109514514</internalNodes>
          <leafValues>
            -5.5259132385253906e-01 7.2679471969604492e-01</leafValues></_>
        <_>
          <internalNodes>
            0 -1 74 -1962764060 -1608299477 -1689796537 906846643
            1921417649 -385625472 1484898538 -170198559</internalNodes>
          <leafValues>
            -7.5680071115493774e-01 5.8806973695755005e-01</leafValues></_></weakClassifiers></_>
    <!-- stage 10 -->
    <_>
      <maxWeakCount>6</maxWeakCount>
      <stageThreshold>-1.1201803684234619e+00</stageThreshold>
      <weakClassifiers>
        <_>
          <internalNodes>
            0 -1 26 -792360445 -2136651775 -2147418097 -715456506
            -1039677277 453183489 -268175185 549833351</internalNodes>
          <leafValues>
            -7.5233644247055054e-01 6.1604094505310059e-01</leafValues></_>
        <_>
          <internalNodes>
            0 -1 31 -67403937 -1346683020 -1082654722 -1089046529
            -402674905 670924631 -168591563 -336102095</internalNodes>
          <leafValues>
            -5.9096688032150269e-01 6.7432516813278198e-01</leafValues></_>
        <_>
          <internalNodes>
            0 -1 76 -271388675 -285217282 -65553 -286335425 -139
            -134348803 -17006763 -5198076</internalNodes>
          <leafValues>
            -5.9159690141677856e-01 6.7738461494445801e-01</leafValues></_>
        <_>
          <internalNodes>
            0 -1 39 -1222410369 -135626754 -10 738098430 -67748
            -1082163205 -939591820 -151715850</internalNodes>
          <leafValues>
            -5.9072607755661011e-01 6.8923646211624146e-01</leafValues></_>
        <_>
          <internalNodes>
            0 -1 52 -287047809 -1364262977 -1359069185 -1427177476
            -310937743 -733937804 -134742202 -983048363</internalNodes>
          <leafValues>
            -5.9743744134902954e-01 7.0640367269515991e-01</leafValues></_>
        <_>
          <internalNodes>
            0 -1 80 -1593704216 -494501824 889323520 -791105400
            -2105532416 -934805504 -1835826766 -205586280</internalNodes>
          <leafValues>
            -6.1010485887527466e-01 6.9904232025146484e-01</leafValues></_></weakClassifiers></_>
    <!-- stage 11 -->
    <_>
      <maxWeakCount>5</maxWeakCount>
      <stageThreshold>-9.6955341100692749e-01</stageThreshold>
      <weakClassifiers>
        <_>
          <internalNodes>
            0 -1 14 1068479443 599474143 -501137150 1074866432
            -1578900857 710090950 -647774071 803201735</internalNodes>
          <leafValues>
            -8.2044887542724609e-01 6.0800665616989136e-01</leafValues></_>
        <_>
          <internalNodes>
            0 -1 86 -1722811557 536920450 805310720 -1234373518
            -1023373300 276856843 -515850047 -134219521</internalNodes>
          <leafValues>
            -5.9871494770050049e-01 6.5727758407592773e-01</leafValues></_>
        <_>
          <internalNodes>
            0 -1 56 -2138527102 -1065293684 -1308621816 -1564016438
            -1028668789 605261312 -754244765 -7370593</internalNodes>
          <leafValues>
            -7.8813886642456055e-01 4.9545022845268250e-01</leafValues></_>
        <_>
          <internalNodes>
            0 -1 90 -1555836021 134434816 -2147417080 -1467662320
            1342406657 -2147450621 -1073496064 115290698</internalNodes>
          <leafValues>
            -7.1796870231628418e-01 5.1869732141494751e-01</leafValues></_>
        <_>
          <internalNodes>
            0 -1 45 -14427141 -92373000 2012905462 -512299012 1333492247
            -1082155010 -1208500396 -1099170324</internalNodes>
          <leafValues>
            -5.6453716754913330e-01 6.8706101179122925e-01</leafValues></_></weakClassifiers></_>
    <!-- stage 12 -->
    <_>
      <maxWeakCount>5</maxWeakCount>
      <stageThreshold>-8.1946498155593872e-01</stageThreshold>
      <weakClassifiers>
        <_>
          <internalNodes>
            0 -1 68 667281279 652656075 -452623616 -1513126463
            -1539013307 1082827144 -465107904 -1513230199</internalNodes>
          <leafValues>
            -7.1428573131561279e-01 7.3033708333969116e-01</leafValues></_>
        <_>
          <internalNodes>
            0 -1 54 655195135 35847041 -1929313015 -272282560
            -1341802057 1136439960 421552128 -1111613238</internalNodes>
          <leafValues>
            -7.2298043966293335e-01 5.6065857410430908e-01</leafValues></_>
        <_>
          <internalNodes>
            0 -1 37 -2139082576 -1088831087 -1790602925 -1089631102
            721434035 466715315 186978325 -1313668800</internalNodes>
          <leafValues>
            -6.4922225475311279e-01 6.3250404596328735e-01</leafValues></_>
        <_>
          <internalNodes>
            0 -1 33 -1531973889 -1347436674 2139029426 -16412 -144179432
            786825087 -143131056 -973637903</internalNodes>
          <leafValues>
            -5.9685981273651123e-01 7.1980309486389160e-01</leafValues></_>
        <_>
          <internalNodes>
            0 -1 50 77873127 631611607 553721728 1032691876 592837561
            -527264608 478392736 1838874754</internalNodes>
          <leafValues>
            -6.8480235338211060e-01 5.8024424314498901e-01</leafValues></_></weakClassifiers></_>
    <!-- stage 13 -->
    <_>
      <maxWeakCount>5</maxWeakCount>
      <stageThreshold>-6.5384262800216675e-01</stageThreshold>
      <weakClassifiers>
        <_>
          <internalNodes>
            0 -1 0 -1326385167 -393225 -1 -393219 -34242561 -1
            -168460295 -168790032</internalNodes>
          <leafValues>
            -6.2564992904663086e-01 7.4389052391052246e-01</leafValues></_>
        <_>
          <internalNodes>
            0 -1 43 604781937 1035994135 -1140777607 530134084
            -1515601989 -1467965276 683716091 665714915</internalNodes>
          <leafValues>
            -7.8834038972854614e-01 5.4793775081634521e-01</leafValues></_>
        <_>
          <internalNodes>
            0 -1 51 285236693 -721350639 -2130700519 1543639104
            -779056908 -626786168 -1954013899 -58677120</internalNodes>
          <leafValues>
            -6.0839492082595825e-01 6.8699210882186890e-01</leafValues></_>
        <_>
          <internalNodes>
            0 -1 72 -1432301328 -290808148 1855684347 -102069059
            -301154366 -1923447810 -5249617 -6583906</internalNodes>
          <leafValues>
            -4.6840274333953857e-01 7.6328170299530029e-01</leafValues></_>
        <_>
          <internalNodes>
            0 -1 58 -662636632 -99578982 -1004267621 -1987799872
            -1316244586 -1588297570 -1983411805 -1074288502</internalNodes>
          <leafValues>
            -6.6024357080459595e-01 6.0526084899902344e-01</leafValues></_></weakClassifiers></_>
    <!-- stage 14 -->
    <_>
      <maxWeakCount>5</maxWeakCount>
      <stageThreshold>-8.0769073963165283e-01</stageThreshold>
      <weakClassifiers>
        <_>
          <internalNodes>
            0 -1 71 366220561 905787733 337972601 534060359 -780012615
            700186772 -922428312 1070537419</internalNodes>
          <leafValues>
            -8.3636361360549927e-01 6.6206896305084229e-01</leafValues></_>
        <_>
          <internalNodes>
            0 -1 77 872421757 -787398459 -2130672579 -608648827
            -259997774 -1283440467 765692897 -1105196784</internalNodes>
          <leafValues>
            -5.8409327268600464e-01 6.9771498441696167e-01</leafValues></_>
        <_>
          <internalNodes>
            0 -1 47 142644475 -1535069500 360785173 1367442441
            -2137900865 -795836183 33590148 -1693808640</internalNodes>
          <leafValues>
            -7.0120584964752197e-01 5.6426334381103516e-01</leafValues></_>
        <_>
          <internalNodes>
            0 -1 4 353374393 -1780391120 159387033 -32505593 -2138534421
            -1551891831 -1538642415 -1103101820</internalNodes>
          <leafValues>
            -6.0128545761108398e-01 6.1307877302169800e-01</leafValues></_>
        <_>
          <internalNodes>
            0 -1 32 -1082917153 -1149304834 -16843076 -1669530756
            2011692926 -403275913 2112945858 -404316674</internalNodes>
          <leafValues>
            -5.4468822479248047e-01 7.0089322328567505e-01</leafValues></_></weakClassifiers></_>
    <!-- stage 15 -->
    <_>
      <maxWeakCount>5</maxWeakCount>
      <stageThreshold>-7.9539585113525391e-01</stageThreshold>
      <weakClassifiers>
        <_>
          <internalNodes>
            0 -1 66 -267325264 -242118351 891655447 -720008688
            -1203657543 -1086807631 -1165972373 -932173816</internalNodes>
          <leafValues>
            -7.7931034564971924e-01 6.3433474302291870e-01</leafValues></_>
        <_>
          <internalNodes>
            0 -1 75 -515059696 -471520396 232452306 -7898938 -1641488966
            -300950156 -2045868875 -68222763</internalNodes>
          <leafValues>
            -4.7869026660919189e-01 7.6979738473892212e-01</leafValues></_>
        <_>
          <internalNodes>
            0 -1 64 872422225 1064503133 -1660776065 1061487061 302225
            -402108415 -1960757816 1066338508</internalNodes>
          <leafValues>
            -8.3618992567062378e-01 4.7214201092720032e-01</leafValues></_>
        <_>
          <internalNodes>
            0 -1 69 1213764173 -5363666 -269488261 2147443583 -411052545
            -478150785 394209079 -134237313</internalNodes>
          <leafValues>
            -5.4302996397018433e-01 6.8915277719497681e-01</leafValues></_>
        <_>
          <internalNodes>
            0 -1 2 285491679 -16678887 1359024605 -1172565988 671146418
            -897056542 -1895807787 -1474297440</internalNodes>
          <leafValues>
            -6.5754663944244385e-01 5.9333699941635132e-01</leafValues></_></weakClassifiers></_>
    <!-- stage 16 -->
    <_>
      <maxWeakCount>5</maxWeakCount>
      <stageThreshold>-6.4327824115753174e-01</stageThreshold>
      <weakClassifiers>
        <_>
          <internalNodes>
            0 -1 61 -715795115 -1688665775 219432213 756105500
            -720530431 1006895108 -993924793 265800719</internalNodes>
          <leafValues>
            -6.7728239297866821e-01 6.3684678077697754e-01</leafValues></_>
        <_>
          <internalNodes>
            0 -1 36 889475293 -707714671 1547701661 -1639448108
            -1978618701 -74153672 -1468003531 -1400853824</internalNodes>
          <leafValues>
            -6.0973954200744629e-01 5.7583373785018921e-01</leafValues></_>
        <_>
          <internalNodes>
            0 -1 40 -1305946947 -214862347 -2049 2013265919 -628183828
            -65765923 -35651873 -8388737</internalNodes>
          <leafValues>
            -4.9492377042770386e-01 7.0612025260925293e-01</leafValues></_>
        <_>
          <internalNodes>
            0 -1 19 -143239681 -289472641 -1146882 -253984898 -9438194
            2013036153 1442753916 -84099073</internalNodes>
          <leafValues>
            -4.7849991917610168e-01 6.5735971927642822e-01</leafValues></_>
        <_>
          <internalNodes>
            0 -1 60 -1940651900 -720729639 84216127 487332075
            -1734799174 -75352062 -1106110198 -2002778086</internalNodes>
          <leafValues>
            -7.0426559448242188e-01 4.7538399696350098e-01</leafValues></_></weakClassifiers></_>
    <!-- stage 17 -->
    <_>
      <maxWeakCount>7</maxWeakCount>
      <stageThreshold>-1.0555340051651001e+00</stageThreshold>
      <weakClassifiers>
        <_>
          <internalNodes>
            0 -1 16 1900361599 -787339705 1073807368 -662486904
            953222813 440664206 554042307 985755970</internalNodes>
          <leafValues>
            -8.7861269712448120e-01 5.6140351295471191e-01</leafValues></_>
        <_>
          <internalNodes>
            0 -1 15 -9536257 -428933202 654092198 -1426526225 2147429212
            -897679366 1610524470 -138478849</internalNodes>
          <leafValues>
            -5.4579931497573853e-01 6.7812383174896240e-01</leafValues></_>
        <_>
          <internalNodes>
            0 -1 55 175967980 140004697 205606914 -2111782656
            -1982690325 591517760 -175973622 -1084519797</internalNodes>
          <leafValues>
            -6.9382101297378540e-01 5.5354833602905273e-01</leafValues></_>
        <_>
          <internalNodes>
            0 -1 88 -102796337 16914206 1073741968 810205378 -263076864
            806441984 -251640926 1060168238</internalNodes>
          <leafValues>
            -6.3695150613784790e-01 5.6554323434829712e-01</leafValues></_>
        <_>
          <internalNodes>
            0 -1 81 -1317488640 -597131232 1113117392 -235490059
            -2118978740 544126917 -1757169482 -207939859</internalNodes>
          <leafValues>
            -5.5917990207672119e-01 6.6795217990875244e-01</leafValues></_>
        <_>
          <internalNodes>
            0 -1 91 -1611331617 -687587319 1342537799 -745405417
            -200744939 537461024 -502732284 -1649133016</internalNodes>
          <leafValues>
            -7.4428844451904297e-01 5.1537156105041504e-01</leafValues></_>
        <_>
          <internalNodes>
            0 -1 59 -1879039922 -153726583 268699151 469930650
            -1073708789 1988689928 -360142194 608348056</internalNodes>
          <leafValues>
            -7.3104244470596313e-01 5.2256625890731812e-01</leafValues></_></weakClassifiers></_>
    <!-- stage 18 -->
    <_>
      <maxWeakCount>7</maxWeakCount>
      <stageThreshold>-1.3028783798217773e+00</stageThreshold>
      <weakClassifiers>
        <_>
          <internalNodes>
            0 -1 30 -135275009 -1350635522 -134828366 -204537882
            -8388780 -302645315 -134482588 -977404571</internalNodes>
          <leafValues>
            -4.3407407402992249e-01 7.4918919801712036e-01</leafValues></_>
        <_>
          <internalNodes>
            0 -1 72 -1433894808 -290812226 -24445230 -391214852
            -1097678902 -1118140482 -542202433 -74737409</internalNodes>
          <leafValues>
            -4.5415741205215454e-01 7.3733925819396973e-01</leafValues></_>
        <_>
          <internalNodes>
            0 -1 48 -357665168 -818217164 2147401310 -1364656400
            -172591276 -142786745 -402677964 -1094799478</internalNodes>
          <leafValues>
            -5.5221682786941528e-01 6.6265511512756348e-01</leafValues></_>
        <_>
          <internalNodes>
            0 -1 81 -1305827192 -731348832 39453250 -204036891
            -1592773693 -1594902579 -412642633 -67373327</internalNodes>
          <leafValues>
            -5.0809711217880249e-01 7.3745560646057129e-01</leafValues></_>
        <_>
          <internalNodes>
            0 -1 17 -22086993 -285280578 -1359026546 -956628993
            1031599943 1179975679 -159384010 -167837826</internalNodes>
          <leafValues>
            -6.0071974992752075e-01 6.6262042522430420e-01</leafValues></_>
        <_>
          <internalNodes>
            0 -1 46 -1364313112 -276935058 -16875614 -956514410
            -278954120 -404852874 -737788 -88044082</internalNodes>
          <leafValues>
            -5.9098362922668457e-01 6.9194924831390381e-01</leafValues></_>
        <_>
          <internalNodes>
            0 -1 85 -1307532920 -1048576000 -2146085760 -1858928381
            -2147442560 8552456 16880326 -1148513376</internalNodes>
          <leafValues>
            -6.3705909252166748e-01 6.6497302055358887e-01</leafValues></_></weakClassifiers></_>
    <!-- stage 19 -->
    <_>
      <maxWeakCount>6</maxWeakCount>
      <stageThreshold>-8.0134135484695435e-01</stageThreshold>
      <weakClassifiers>
        <_>
          <internalNodes>
            0 -1 44 1476444177 545267712 16777237 194576513 -1879013376
            294158376 -134182903 193593483</internalNodes>
          <leafValues>
            -8.1420767307281494e-01 6.7034834623336792e-01</leafValues></_>
        <_>
          <internalNodes>
            0 -1 83 -792182656 -242491389 16777217 1393099265
            -1206697965 1476493704 -251641845 -1738452734</internalNodes>
          <leafValues>
            -5.8601665496826172e-01 5.8723914623260498e-01</leafValues></_>
        <_>
          <internalNodes>
            0 -1 65 -804368086 -619442174 822157713 -1039638528
            -1795124816 -1794473958 -2147450615 -33422654</internalNodes>
          <leafValues>
            -5.3044259548187256e-01 6.9942224025726318e-01</leafValues></_>
        <_>
          <internalNodes>
            0 -1 79 -1149073238 -286303936 578164320 -230461708
            -1918177884 9730606 -1544776558 -604010499</internalNodes>
          <leafValues>
            -5.2606707811355591e-01 7.4071902036666870e-01</leafValues></_>
        <_>
          <internalNodes>
            0 -1 84 -2096496512 -1046802176 -1853669248 -246972096
            134258946 536870912 -1568632415 -1327855192</internalNodes>
          <leafValues>
            -5.3675007820129395e-01 6.9834280014038086e-01</leafValues></_>
        <_>
          <internalNodes>
            0 -1 87 -1127700072 -801590076 872308872 -541234064
            -1476606368 -2124124635 -723478276 -1276160986</internalNodes>
          <leafValues>
            -5.2227813005447388e-01 7.7521038055419922e-01</leafValues></_></weakClassifiers></_></stages>
  <features>
    <_>
      <rect>
        0 0 11 15</rect></_>
    <_>
      <rect>
        0 0 12 29</rect></_>
    <_>
      <rect>
        0 2 9 4</rect></_>
    <_>
      <rect>
        0 3 12 29</rect></_>
    <_>
      <rect>
        0 6 5 3</rect></_>
    <_>
      <rect>
        0 6 9 28</rect></_>
    <_>
      <rect>
        0 7 9 27</rect></_>
    <_>
      <rect>
        0 9 12 27</rect></_>
    <_>
      <rect>
        0 25 13 11</rect></_>
    <_>
      <rect>
        0 29 13 7</rect></_>
    <_>
      <rect>
        0 31 13 14</rect></_>
    <_>
      <rect>
        0 33 13 11</rect></_>
    <_>
      <rect>
        0 34 11 14</rect></_>
    <_>
      <rect>
        0 35 6 7</rect></_>
    <_>
      <rect>
        0 36 13 18</rect></_>
    <_>
      <rect>
        0 37 2 3</rect></_>
    <_>
      <rect>
        0 37 9 17</rect></_>
    <_>
      <rect>
        0 38 2 2</rect></_>
    <_>
      <rect>
        0 38 2 3</rect></_>
    <_>
      <rect>
        0 40 2 3</rect></_>
    <_>
      <rect>
        0 40 6 5</rect></_>
    <_>
      <rect>
        0 41 4 3</rect></_>
    <_>
      <rect>
        0 42 4 4</rect></_>
    <_>
      <rect>
        0 43 2 4</rect></_>
    <_>
      <rect>
        0 46 3 4</rect></_>
    <_>
      <rect>
        0 50 3 3</rect></_>
    <_>
      <rect>
        1 11 12 13</rect></_>
    <_>
      <rect>
        1 25 7 13</rect></_>
    <_>
      <rect>
        1 34 13 18</rect></_>
    <_>
      <rect>
        1 37 3 4</rect></_>
    <_>
      <rect>
        1 45 3 3</rect></_>
    <_>
      <rect>
        1 50 3 4</rect></_>
    <_>
      <rect>
        2 39 2 3</rect></_>
    <_>
      <rect>
        2 47 3 4</rect></_>
    <_>
      <rect>
        2 47 5 3</rect></_>
    <_>
      <rect>
        3 0 4 4</rect></_>
    <_>
      <rect>
        3 0 11 4</rect></_>
    <_>
      <rect>
        3 9 12 7</rect></_>
    <_>
      <rect>
        3 34 8 6</rect></_>
    <_>
      <rect>
        3 38 1 4</rect></_>
    <_>
      <rect>
        3 39 10 8</rect></_>
    <_>
      <rect>
        3 44 6 5</rect></_>
    <_>
      <rect>
        3 46 3 3</rect></_>
    <_>
      <rect>
        3 51 11 10</rect></_>
    <_>
      <rect>
        4 29 12 7</rect></_>
    <_>
      <rect>
        4 36 2 4</rect></_>
    <_>
      <rect>
        4 43 1 1</rect></_>
    <_>
      <rect>
        5 35 10 9</rect></_>
    <_>
      <rect>
        5 42 1 1</rect></_>
    <_>
      <rect>
        5 50 3 3</rect></_>
    <_>
      <rect>
        5 60 11 10</rect></_>
    <_>
      <rect>
        6 1 10 2</rect></_>
    <_>
      <rect>
        6 49 3 4</rect></_>
    <_>
      <rect>
        7 32 11 11</rect></_>
    <_>
      <rect>
        7 37 11 6</rect></_>
    <_>
      <rect>
        8 36 6 6</rect></_>
    <_>
      <rect>
        8 41 6 6</rect></_>
    <_>
      <rect>
        9 41 5 4</rect></_>
    <_>
      <rect>
        9 42 6 8</rect></_>
    <_>
      <rect>
        9 49 9 6</rect></_>
    <_>
      <rect>
        10 6 10 8</rect></_>
    <_>
      <rect>
        10 9 10 27</rect></_>
    <_>
      <rect>
        10 29 10 20</rect></_>
    <_>
      <rect>
        10 38 6 8</rect></_>
    <_>
      <rect>
        10 53 10 12</rect></_>
    <_>
      <rect>
        11 44 6 5</rect></_>
    <_>
      <rect>
        12 0 9 15</rect></_>
    <_>
      <rect>
        13 17 9 12</rect></_>
    <_>
      <rect>
        13 32 9 19</rect></_>
    <_>
      <rect>
        14 40 5 5</rect></_>
    <_>
      <rect>
        15 0 4 3</rect></_>
    <_>
      <rect>
        16 47 8 14</rect></_>
    <_>
      <rect>
        18 44 1 1</rect></_>
    <_>
      <rect>
        19 33 7 19</rect></_>
    <_>
      <rect>
        19 40 3 3</rect></_>
    <_>
      <rect>
        19 46 1 1</rect></_>
    <_>
      <rect>
        21 1 4 3</rect></_>
    <_>
      <rect>
        21 2 6 4</rect></_>
    <_>
      <rect>
        22 32 6 13</rect></_>
    <_>
      <rect>
        22 47 1 1</rect></_>
    <_>
      <rect>
        22 49 1 1</rect></_>
    <_>
      <rect>
        24 47 1 1</rect></_>
    <_>
      <rect>
        25 3 3 3</rect></_>
    <_>
      <rect>
        25 7 5 12</rect></_>
    <_>
      <rect>
        25 45 1 1</rect></_>
    <_>
      <rect>
        25 47 1 1</rect></_>
    <_>
      <rect>
        28 33 4 9</rect></_>
    <_>
      <rect>
        28 46 1 1</rect></_>
    <_>
      <rect>
        29 28 3 10</rect></_>
    <_>
      <rect>
        31 38 3 7</rect></_>
    <_>
      <rect>
        31 41 3 13</rect></_>
    <_>
      <rect>
        34 2 2 5</rect></_></features></cascade>
</opencv_storage>
